{
  "version": 1,
  "items_signature": "26997ac6ea3a50661c48f4ebc52c6eb5695186b93403b5daa7ce00e3bea26bbe",
  "items_count": 228,
  "batch_pointer": 29,
  "last_run_at_utc": "2026-05-01T06:24:47.332798+00:00",
  "last_status": "ok",
  "last_batch_items": [
    "M4A1-S | Blood Tiger (Factory New)",
    "MP9 | Orange Peel (Factory New)",
    "P2000 | Wicked Sick (Field-Tested)",
    "AK-47 | Steel Delta (Factory New)",
    "AK-47 | Safari Mesh (Factory New)"
  ],
  "last_error": null,
  "last_finished_at_utc": "2026-05-01T06:25:46.870815+00:00",
  "last_successful_monitoring_at_utc": "2026-05-01T06:25:46.870815+00:00",
  "last_failed_monitoring_at_utc": null,
  "consecutive_errors": 0,
  "last_listing_errors": [],
  "last_listing_error_count": 0,
  "last_listing_rows": 724,
  "last_enriched_rows": 724,
  "last_opportunities_rows": 0,
  "last_alert_stats": {
    "loaded": 0,
    "filtered": 0,
    "considered": 0,
    "sent": 0,
    "skipped": 0
  },
  "last_batch_start_pointer": 24,
  "sent_alerts": {
    "listing:529878490348072152": {
      "sent_at_utc": "2026-05-01T05:03:55.091555+00:00",
      "item": "Desert Eagle | Mint Fan (Factory New)",
      "listing_id": "529878490348072152",
      "spread_hybrid_disc": 0.0891105290538061
    }
  },
  "last_alert_sent_at_utc": "2026-05-01T05:03:55.091631+00:00"
}
